bioinfo_toolset/__init__.py
bioinfo_toolset/bit.py
bioinfo_toolset/modules/__init__.py
bioinfo_toolset/modules/helper.py
bioinfo_toolset/modules/hgvs.py
bioinfo_toolset/modules/liftover.py
bioinfo_toolset/modules/phenotype.py
bioinfo_toolset/modules/variant_recoder.py
bioinfo_toolset/modules/vep.py
bioinfo_toolset/modules/vep_offline.py
bioinfo_toolset/modules/vrs.py
bioinfo_toolset-1.4.dist-info/METADATA
bioinfo_toolset-1.4.dist-info/WHEEL
bioinfo_toolset-1.4.dist-info/entry_points.txt
bioinfo_toolset-1.4.dist-info/top_level.txt
bioinfo_toolset-1.4.dist-info/RECORD
