Metadata-Version: 2.1
Name: bioinfo-toolset
Version: 1.4
Summary: Python Rules Evaluator
Home-page: https://github.com/dameyerdave/bioinfo-toolset
Author: David Meyer
Author-email: dameyerdave@gmail.com
License: UNKNOWN
Platform: UNKNOWN
Classifier: Programming Language :: Python :: 3
Classifier: License :: OSI Approved :: MIT License
Classifier: Operating System :: OS Independent
Requires-Python: >=3.5
Requires-Dist: liftover
Requires-Dist: click
Requires-Dist: friendlylog
Requires-Dist: termcolor
Requires-Dist: tqdm
Requires-Dist: hgvs
Requires-Dist: jsonschema
Requires-Dist: docker
Requires-Dist: ga4gh.vrs[extras]
